bsapi/__init__.py
bsapi/base.py
bsapi/models.py
bsapi/settings.py
bsapi/app_automate/__init__.py
bsapi/app_automate/appium/__init__.py
bsapi/app_automate/appium/apps.py
bsapi/app_automate/appium/builds.py
bsapi/app_automate/appium/devices.py
bsapi/app_automate/appium/plans.py
bsapi/app_automate/appium/projects.py
bsapi/app_automate/appium/responses.py
bsapi/app_automate/appium/sessions.py
bsapi/automate/__init__.py
bsapi/automate/selenium/__init__.py
bsapi/automate/selenium/browsers.py
bsapi/automate/selenium/builds.py
bsapi/automate/selenium/plans.py
bsapi/automate/selenium/projects.py
bsapi/automate/selenium/sessions.py
bsapi-0.1.6.dist-info/LICENSE
bsapi-0.1.6.dist-info/METADATA
bsapi-0.1.6.dist-info/WHEEL
bsapi-0.1.6.dist-info/top_level.txt
bsapi-0.1.6.dist-info/RECORD
