Metadata-Version: 2.1
Name: bsapi
Version: 0.1.6
Summary: A package for interacting with the BrowserStack REST apis
Home-page: https://github.com/fictitiouswizard/bsapi
Author: Jason Sanders
License: GPL-3.0
Project-URL: documentation, https://bsapi.readthedocs.io/
Project-URL: Source, https://github.com/fictitiouswizard/bsapi
Project-URL: Funding, https://liberapay.com/fictitiouswizard/
Classifier: Programming Language :: Python :: 3
Classifier: License :: OSI Approved :: GNU General Public License v3 (GPLv3)
License-File: LICENSE
Requires-Dist: requests
Requires-Dist: python-dotenv
Requires-Dist: urllib3
Requires-Dist: importlib ; python_version == "2.6"
